value_lookup/__init__.py
value_lookup/lookup.py
value_lookup/value_lookup.py
value_lookup-0.1.0.dist-info/METADATA
value_lookup-0.1.0.dist-info/WHEEL
value_lookup-0.1.0.dist-info/top_level.txt
value_lookup-0.1.0.dist-info/RECORD
