Metadata-Version: 2.1
Name: value-lookup
Version: 0.1.0
Summary: Beta library
Home-page: https://value-lookup.readthedocs.io/
Author: Euclidio Venâncio
Author-email: euclidiodagraca@gmail.com
License: MIT
Platform: UNKNOWN
Classifier: Intended Audience :: Developers
Classifier: License :: OSI Approved :: MIT License
Classifier: Programming Language :: Python
Classifier: Programming Language :: Python :: 3.9
Classifier: Operating System :: OS Independent
